brainplus/__init__.py
brainplus/__main__.py
brainplus/brainplus.py
brainplus/test
brainplus/test.bf
brainplus-1.0.dist-info/entry_points.txt
brainplus-1.0.dist-info/LICENSE
brainplus-1.0.dist-info/WHEEL
brainplus-1.0.dist-info/METADATA
brainplus-1.0.dist-info/RECORD
