Metadata-Version: 2.1
Name: brainplus
Version: 1.0
Summary: A compiler for Brainfuck+ esotheric language.
Author-email: Elia Toselli <elia.toselli@outlook.it>
Requires-Python: >= 3.10
Classifier: License :: OSI Approved :: GNU General Public License v3 or later (GPLv3+)
Project-URL: Home, https://github.com/hilcon222/brainplus
